taqu/__init__.py
taqu/client.py
taqu/exceptions.py
taqu/utils.py
taqu/worker.py
taqu/aio/__init__.py
taqu/aio/client.py
taqu/aio/worker.py
taqu-1.0.0.dist-info/LICENSE
taqu-1.0.0.dist-info/METADATA
taqu-1.0.0.dist-info/WHEEL
taqu-1.0.0.dist-info/top_level.txt
taqu-1.0.0.dist-info/RECORD
