Metadata-Version: 2.1
Name: taqu
Version: 1.0.0
Summary: Taqu Task Queue system
Home-page: https://github.com/lietu/taqu
Author: Janne Enberg
Author-email: janne.enberg@lietu.net
License: UNKNOWN
Project-URL: Bug Reports, https://github.com/lietu/taqu/issues
Project-URL: Source, https://github.com/lietu/taqu/
Keywords: task queue azure service bus
Platform: UNKNOWN
Classifier: License :: OSI Approved :: BSD License
Classifier: Programming Language :: Python :: 3
Classifier: Programming Language :: Python :: 3.6
Classifier: Programming Language :: Python :: 3.7
Classifier: Programming Language :: Python :: 3.8
Requires-Python: >=3.6,<4
Requires-Dist: pydantic (<2,>=1.4)
Requires-Dist: async-generator (~=1.10)
Provides-Extra: azure
Requires-Dist: azure-servicebus (<1,>=0.50) ; extra == 'azure'
